yostate/__init__.py
yostate/async_crawler.py
yostate/exceptions.py
yostate/locators.py
yostate/router.py
yostate/state_class_locator_validators.py
yostate/states.py
yostate/sync_crawler.py
yostate-1.0.0.dist-info/METADATA
yostate-1.0.0.dist-info/WHEEL
yostate-1.0.0.dist-info/RECORD
